{
    "data": [
        {
            "Low-vulnerability": [
                "X-Generator: Drupal 7 (http://drupal.org)",
                "X-Frame-Options: Not Enforced",
                "Robots.txt Found: https://www.apu.edu.my/robots.txt",
                "https://www.apu.edu.my/.default.txt",
                "https://www.apu.edu.my/.bash_profile.txt",
                "https://www.apu.edu.my/.logs.txt",
                "https://www.apu.edu.my/.db_config.txt",
                "https://www.apu.edu.my/.bashrc.txt",
                "https://www.apu.edu.my/.old.txt",
                "https://www.apu.edu.my/.secret.txt",
                "https://www.apu.edu.my/.queries.txt",
                "https://www.apu.edu.my/.private.txt",
                "https://www.apu.edu.my/.temp.txt",
                "https://www.apu.edu.my/.temp2.txt",
                "https://www.apu.edu.my/.sql.txt",
                "https://www.apu.edu.my/.query.txt",
                "https://www.apu.edu.my/.db_config.php",
                "https://www.apu.edu.my/.logs.php",
                "https://www.apu.edu.my/.bashrc.php",
                "https://www.apu.edu.my/.bash_profile.php",
                "https://www.apu.edu.my/.default.php",
                "https://www.apu.edu.my/.old.php",
                "https://www.apu.edu.my/.queries.php",
                "https://www.apu.edu.my/.query.php",
                "https://www.apu.edu.my/.private.php",
                "https://www.apu.edu.my/.secret.php",
                "https://www.apu.edu.my/.sql.php",
                "https://www.apu.edu.my/.temp2.php",
                "https://www.apu.edu.my/.temp.php",
                "https://www.apu.edu.my/install.php",
                "https://www.apu.edu.my/.bash_profile/",
                "https://www.apu.edu.my/.bashrc/",
                "https://www.apu.edu.my/.db_config/",
                "https://www.apu.edu.my/.default/",
                "https://www.apu.edu.my/.logs/",
                "https://www.apu.edu.my/.query/",
                "https://www.apu.edu.my/.old/",
                "https://www.apu.edu.my/.queries/",
                "https://www.apu.edu.my/.private/",
                "https://www.apu.edu.my/.secret/",
                "https://www.apu.edu.my/.temp2/",
                "https://www.apu.edu.my/.sql/",
                "https://www.apu.edu.my/.temp/",
                "https://www.apu.edu.my/0/",
                "https://www.apu.edu.my/Temp/",
                "https://www.apu.edu.my/Test/",
                "https://www.apu.edu.my/sitemap/",
                "https://www.apu.edu.my/temp/",
                "https://www.apu.edu.my/test/",
                "https://www.apu.edu.my/.bash_profile.html",
                "https://www.apu.edu.my/.db_config.html",
                "https://www.apu.edu.my/.bashrc.html",
                "https://www.apu.edu.my/.default.html",
                "https://www.apu.edu.my/.logs.html",
                "https://www.apu.edu.my/.private.html",
                "https://www.apu.edu.my/.query.html",
                "https://www.apu.edu.my/.queries.html",
                "https://www.apu.edu.my/.old.html",
                "https://www.apu.edu.my/.secret.html",
                "https://www.apu.edu.my/.sql.html",
                "https://www.apu.edu.my/.temp2.html",
                "https://www.apu.edu.my/.temp.html"
            ],
            "Medium-vulnerability": [
                "EDB-ID: 46510 \"Drupal < 8.5.11 / < 8.6.10 - RESTful Web Services unserialize() Remote Command Execution (Metasploit)\"",
                "EDB-ID: 44448 \"Drupal < 8.3.9 / < 8.4.6 / < 8.5.1 - 'Drupalgeddon2' Remote Code Execution (PoC)\"",
                "EDB-ID: 44449 \"Drupal < 7.58 / < 8.3.9 / < 8.4.6 / < 8.5.1 - 'Drupalgeddon2' Remote Code Execution\"",
                "EDB-ID: 44482 \"Drupal < 8.3.9 / < 8.4.6 / < 8.5.1 - 'Drupalgeddon2' Remote Code Execution (Metasploit)\""
            ],
            "High-vulnerability": [],
            "Cms-info": [
                "Threads: 5",
                "Server: Apache",
                "Strict-Transport-Security: Not Enforced",
                "X-Content-Security-Policy: Not Enforced",
                "CMS Detection: Drupal",
                "Drupal Version: 7.59",
                "Drupal Theme: APU",
                "Autocomplete Off Not Found: https://www.apu.edu.my/user/",
                "https://www.apu.edu.my/robots.txt",
                "https://www.apu.edu.my/sites/README.txt",
                "https://www.apu.edu.my/themes/README.txt",
                "https://www.apu.edu.my/profiles/README.txt",
                "https://www.apu.edu.my/modules/README.txt",
                "Forgotten Password Allows Username Enumeration: https://www.apu.edu.my/user/password"
            ],
            "countLow": 62,
            "countMed": 4,
            "countHigh": 0,
            "countTotal": 66
        }
    ]
}